README.rst
setup.py
lecloud/__init__.py
lecloud/codes.py
lecloud/conn.py
lecloud/errors.py
lecloud/regions.py
lecloud.egg-info/PKG-INFO
lecloud.egg-info/SOURCES.txt
lecloud.egg-info/dependency_links.txt
lecloud.egg-info/requires.txt
lecloud.egg-info/top_level.txt
lecloud/actions/__init__.py
lecloud/actions/api.py
lecloud/actions/instances.py
lecloud/actions/networks.py
lecloud/actions/params.py
lecloud/actions/volumes.py
tests/__init__.py
tests/usecases.py