Metadata-Version: 1.0
Name: lecloud
Version: 0.0.1
Summary: Lecloud SDK python version
Home-page: http://lecloud.com
Author: lecloud@gmail.com
Author-email: UNKNOWN
License: MIT
Platform: UNKNOWN
